oarepo_enrollments/__init__.py
oarepo_enrollments/api.py
oarepo_enrollments/builtin_handlers.py
oarepo_enrollments/cli.py
oarepo_enrollments/config.py
oarepo_enrollments/ext.py
oarepo_enrollments/fields.py
oarepo_enrollments/models.py
oarepo_enrollments/proxies.py
oarepo_enrollments/signals.py
oarepo_enrollments/version.py
oarepo_enrollments/alembic/16ffa6cb5954_actions.py
oarepo_enrollments/alembic/3eb23e67dae3_create_oarepo_enrollment_branch.py
oarepo_enrollments/alembic/816163ff5ad9_model.py
oarepo_enrollments/alembic/90a9bd726859_parent_enrollment.py
oarepo_enrollments/views/__init__.py
oarepo_enrollments/views/api.py
oarepo_enrollments/views/ui.py
oarepo_enrollments/views/templates/oarepo/enrollment/accept.html
oarepo_enrollments/views/templates/oarepo/enrollment/base.html
oarepo_enrollments/views/templates/oarepo/enrollment/failure.html
oarepo_enrollments/views/templates/oarepo/enrollment/reject.html
oarepo_enrollments/views/templates/oarepo/enrollment/success.html
oarepo_enrollments-1.2.2.dist-info/LICENSE
oarepo_enrollments-1.2.2.dist-info/METADATA
oarepo_enrollments-1.2.2.dist-info/WHEEL
oarepo_enrollments-1.2.2.dist-info/entry_points.txt
oarepo_enrollments-1.2.2.dist-info/top_level.txt
oarepo_enrollments-1.2.2.dist-info/RECORD
